greenlight/__init__.py
greenlight/admin.py
greenlight/app_settings.py
greenlight/apps.py
greenlight/auth_hooks.py
greenlight/models.py
greenlight/tasks.py
greenlight/urls.py
greenlight/utils.py
greenlight/views.py
greenlight/locale/.gitkeep
greenlight/migrations/0001_initial.py
greenlight/migrations/0002_webhook_greenlightconfig.py
greenlight/migrations/0003_remove_greenlightconfig_staging_systems_and_more.py
greenlight/migrations/0004_webhook_greenlightconfig.py
greenlight/migrations/0005_create_default_config.py
greenlight/migrations/0006_alter_general_options_alter_webhook_options_and_more.py
greenlight/migrations/0007_remove_greenlightconfig_doctrine_id_and_more.py
greenlight/migrations/0008_remove_greenlightconfig_current_status.py
greenlight/migrations/0009_discordmessageconfig.py
greenlight/migrations/0010_remove_discordmessageconfig_doctrine_group_and_more.py
greenlight/migrations/0011_discordmessageconfig_doctrine_gif_url_and_more.py
greenlight/migrations/__init__.py
greenlight/static/example/.gitkeep
greenlight/templates/greenlight/base.html
greenlight/templates/greenlight/fc_panel.html
greenlight/templates/greenlight/index.html
greenlight/templates/greenlight/status_panel.html
greenlight/tests/__init__.py
greenlight/tests/test_example.py
aa_greenlight-1.2.0.dist-info/METADATA
aa_greenlight-1.2.0.dist-info/WHEEL
aa_greenlight-1.2.0.dist-info/licenses/LICENSE
aa_greenlight-1.2.0.dist-info/RECORD
